channels-stubs/__init__.pyi
channels-stubs/apps.pyi
channels-stubs/auth.pyi
channels-stubs/consumer.pyi
channels-stubs/db.pyi
channels-stubs/exceptions.pyi
channels-stubs/layers.pyi
channels-stubs/middleware.pyi
channels-stubs/py.typed
channels-stubs/routing.pyi
channels-stubs/sessions.pyi
channels-stubs/utils.pyi
channels-stubs/worker.pyi
channels-stubs/generic/__init__.pyi
channels-stubs/generic/http.pyi
channels-stubs/generic/websocket.pyi
channels-stubs/management/__init__.pyi
channels-stubs/management/commands/__init__.pyi
channels-stubs/management/commands/runworker.pyi
channels-stubs/security/__init__.pyi
channels-stubs/security/websocket.pyi
channels-stubs/testing/__init__.pyi
channels-stubs/testing/application.pyi
channels-stubs/testing/http.pyi
channels-stubs/testing/live.pyi
channels-stubs/testing/websocket.pyi
channels_stubs-0.1.9.dist-info/METADATA
channels_stubs-0.1.9.dist-info/WHEEL
channels_stubs-0.1.9.dist-info/licenses/AUTHORS.rst
channels_stubs-0.1.9.dist-info/licenses/LICENSE
channels_stubs-0.1.9.dist-info/RECORD
