Metadata-Version: 2.4
Name: channels-stubs
Version: 0.1.9
Summary: Stubs for django channels
Project-URL: Homepage, https://github.com/huynguyengl99/channels-stubs
Project-URL: Repository, https://github.com/huynguyengl99/channels-stubs
Author-email: Huy Nguyen <danghuy1999@gmail.com>
License: MIT License
License-File: AUTHORS.rst
License-File: LICENSE
Classifier: Environment :: Web Environment
Classifier: Intended Audience :: Developers
Classifier: Intended Audience :: Information Technology
Classifier: License :: OSI Approved :: BSD License
Classifier: Operating System :: OS Independent
Classifier: Programming Language :: Python :: 3
Classifier: Programming Language :: Python :: 3 :: Only
Classifier: Programming Language :: Python :: 3.9
Classifier: Programming Language :: Python :: 3.10
Classifier: Programming Language :: Python :: 3.11
Classifier: Programming Language :: Python :: 3.12
Classifier: Topic :: Internet :: WWW/HTTP
Classifier: Topic :: Internet :: WWW/HTTP :: Dynamic Content
Classifier: Topic :: Software Development
Classifier: Topic :: Software Development :: Libraries
Classifier: Topic :: Software Development :: Libraries :: Application Frameworks
Requires-Python: <4.0,>=3.9
Requires-Dist: channels>=4
Requires-Dist: django-stubs<6,>=4.2.0
Requires-Dist: django<6,>=4.2
